<?xml version="1.0" encoding="utf-8" standalone="yes"?>
<images>
  <image>
    <imageName>P1010057.JPG</imageName>
    <resolution x="640" y="480" />
    <words>
      <word x="11" y="125" width="620" height="138">
        <character x="11" y="125" width="92" height="103" char="둔" />
        <character x="138" y="131" width="105" height="94" char="산" />
        <character x="280" y="134" width="102" height="93" char="돌" />
        <character x="407" y="140" width="107" height="84" char="구" />
        <character x="543" y="144" width="88" height="74" char="이" />
      </word>
      <word x="499" y="227" width="127" height="36">
        <character x="499" y="229" width="25" height="30" char="4" />
        <character x="526" y="228" width="19" height="33" char="8" />
        <character x="545" y="227" width="21" height="33" char="2" />
        <character x="586" y="228" width="21" height="32" char="5" />
        <character x="608" y="230" width="18" height="33" char="9" />
      </word>
    </words>
    <illumination>no</illumination>
    <difficulty>3</difficulty>
    <tag>
    </tag>
  </image>
</images>