<?xml version="1.0" encoding="utf-8" standalone="yes"?>
<images>
  <image>
    <imageName>P090911040.jpg</imageName>
    <resolution x="640" y="480" />
    <words>
      <word x="37" y="46" width="553" height="418">
        <character x="37" y="325" width="183" height="139" char="사" />
        <character x="218" y="293" width="132" height="140" char="요" />
        <character x="311" y="279" width="143" height="101" char="나" />
        <character x="453" y="287" width="137" height="122" char="라" />
      </word>
      <word x="62" y="46" width="508" height="218">
        <character x="62" y="46" width="186" height="131" char="사" />
        <character x="177" y="128" width="152" height="136" char="요" />
        <character x="275" y="96" width="147" height="111" char="나" />
        <character x="421" y="87" width="149" height="120" char="라" />
      </word>
    </words>
    <illumination>no</illumination>
    <difficulty>2</difficulty>
    <tag>
    </tag>
  </image>
</images>