<?xml version="1.0" encoding="utf-8" standalone="yes"?>
<images>
  <image>
    <imageName>DSC03537.JPG</imageName>
    <resolution x="640" y="480" />
    <words>
      <word x="112" y="17" width="486" height="182">
        <character x="112" y="25" width="86" height="96" char="다" />
        <character x="196" y="23" width="85" height="95" char="산" />
        <character x="281" y="25" width="74" height="95" char="전" />
        <character x="357" y="23" width="80" height="87" char="기" />
        <character x="436" y="18" width="83" height="90" char="학" />
        <character x="519" y="17" width="79" height="91" char="원" />
      </word>
      <word x="119" y="117" width="469" height="82">
        <character x="119" y="134" width="45" height="64" char="0" />
        <character x="162" y="132" width="41" height="67" char="4" />
        <character x="203" y="132" width="42" height="64" char="2" />
        <character x="267" y="130" width="44" height="64" char="3" />
        <character x="311" y="134" width="39" height="57" char="8" />
        <character x="353" y="128" width="37" height="61" char="3" />
        <character x="423" y="127" width="42" height="59" char="8" />
        <character x="465" y="125" width="39" height="61" char="2" />
        <character x="504" y="121" width="42" height="62" char="8" />
        <character x="548" y="117" width="40" height="66" char="8" />
      </word>
    </words>
    <illumination>no</illumination>
    <difficulty>3</difficulty>
    <tag>
    </tag>
  </image>
</images>