<?xml version="1.0" encoding="utf-8" standalone="yes"?>
<images>
  <image>
    <imageName>P090903021.jpg</imageName>
    <resolution x="640" y="480" />
    <words>
      <word x="137" y="113" width="403" height="172">
        <character x="137" y="113" width="135" height="171" char="닥" />
        <character x="271" y="113" width="107" height="172" char="터" />
        <character x="374" y="115" width="166" height="158" char="스" />
      </word>
    </words>
    <illumination>no</illumination>
    <difficulty>1</difficulty>
    <tag>
    </tag>
  </image>
</images>