<?xml version="1.0" encoding="utf-8" standalone="yes"?>
<images>
  <image>
    <imageName>DSC02705.JPG</imageName>
    <resolution x="640" y="480" />
    <words>
      <word x="39" y="201" width="541" height="109">
        <character x="39" y="201" width="70" height="108" char="무" />
        <character x="127" y="201" width="67" height="104" char="인" />
        <character x="212" y="205" width="59" height="102" char="민" />
        <character x="286" y="202" width="67" height="106" char="원" />
        <character x="366" y="204" width="61" height="106" char="발" />
        <character x="442" y="207" width="62" height="97" char="급" />
        <character x="517" y="206" width="63" height="99" char="기" />
      </word>
    </words>
    <illumination>no</illumination>
    <difficulty>1</difficulty>
    <tag>
    </tag>
  </image>
</images>