<?xml version="1.0" encoding="utf-8" standalone="yes"?>
<images>
  <image>
    <imageName>DSC03603.JPG</imageName>
    <resolution x="640" y="480" />
    <words>
      <word x="166" y="50" width="364" height="395">
        <character x="202" y="50" width="17" height="51" char="1" />
        <character x="224" y="53" width="38" height="45" char="0" />
        <character x="262" y="52" width="29" height="49" char="3" />
        <character x="292" y="53" width="59" height="52" char="동" />
      </word>
      <word x="166" y="146" width="364" height="77">
        <character x="166" y="146" width="74" height="71" char="상" />
        <character x="239" y="147" width="71" height="70" char="아" />
        <character x="306" y="147" width="74" height="76" char="아" />
        <character x="381" y="153" width="69" height="67" char="파" />
        <character x="450" y="152" width="80" height="63" char="트" />
      </word>
      <word x="319" y="237" width="38" height="41">
        <character x="319" y="237" width="38" height="41" char="1" />
      </word>
      <word x="301" y="281" width="68" height="50">
        <character x="301" y="281" width="21" height="45" char="4" />
        <character x="321" y="287" width="22" height="41" char="3" />
        <character x="342" y="287" width="27" height="44" char="5" />
      </word>
      <word x="188" y="383" width="182" height="62">
        <character x="188" y="384" width="36" height="48" char="1" />
        <character x="224" y="385" width="42" height="53" char="0" />
        <character x="265" y="386" width="36" height="49" char="6" />
        <character x="305" y="383" width="65" height="62" char="동" />
      </word>
    </words>
    <illumination>no</illumination>
    <difficulty>1</difficulty>
    <tag>
    </tag>
  </image>
</images>