<?xml version="1.0" encoding="utf-8" standalone="yes"?>
<images>
  <image>
    <imageName>DSC02652.JPG</imageName>
    <resolution x="640" y="480" />
    <words>
      <word x="145" y="103" width="333" height="234">
        <character x="145" y="193" width="100" height="130" char="노" />
        <character x="254" y="193" width="105" height="138" char="래" />
        <character x="373" y="201" width="105" height="136" char="방" />
      </word>
      <word x="175" y="103" width="289" height="83">
        <character x="175" y="103" width="66" height="83" char="궁" />
        <character x="388" y="104" width="76" height="81" char="전" />
      </word>
    </words>
    <illumination>no</illumination>
    <difficulty>1</difficulty>
    <tag>
    </tag>
  </image>
</images>